sns_message_validator/__init__.py
sns_message_validator/exceptions.py
sns_message_validator/sns_message_type.py
sns_message_validator/sns_message_validator.py
aws_sns_message_validator-0.0.5.dist-info/LICENSE
aws_sns_message_validator-0.0.5.dist-info/METADATA
aws_sns_message_validator-0.0.5.dist-info/WHEEL
aws_sns_message_validator-0.0.5.dist-info/top_level.txt
aws_sns_message_validator-0.0.5.dist-info/RECORD
