Metadata-Version: 2.1
Name: aws-sns-message-validator
Version: 0.0.5
Summary: Validator for AWS SNS messages.
Home-page: https://github.com/wlwg/aws-sns-message-validator
Author: https://github.com/wlwg
License: UNKNOWN
Platform: UNKNOWN
Requires-Python: >=3.6
Requires-Dist: requests (>=2.24.0)
Requires-Dist: requests-cache (>=0.8.0)
Requires-Dist: cryptography (>=3.3.2)
